{"card_name": "D'd'wid, Oathbound", "color": "UB", "rarity": "uncommon", "type": "Legendary Creature \u2013 Plant Faerie Warlock", "number": 188, "color_identity": "UB", "cost": "{1}{U}{B}", "rules_text": "When this creature enters, scry 1. You lose 1 life.\nWhenever you cast your second spell each turn, you may return this card from your graveyard to your hand.", "pt": "3/1", "special_text": "", "shape": "normal", "set": "PRU", "loyalty": "", "notes": "Not fully happy with this one. Maybe ward with mana? Or put on bottom of library to steal permanently\n\nUB\n\nCommon Mechanics: Strategize\n\nTheme: Double-Spell\n\nA medium-fast deck that gains tempo with bounce spells, removal spells, and counterspells\n\nZZZ\n\n5/3? Ward \u2014 Discard a Card?\nChanged since August Optional\n\nNew design needed. Needs to be something a tempo deck wants and trigger off surge and feel like an oathmage. Reanimate? Steal things from graveyards? exchange control? return this from graveyard to hand?", "image_type": "png"}